{
 "title": "Solo Star",
 "artist": "Solange",
 "year": "2021",
 "trackCount": 37,
 "tracks": [
  {
   "title": "Feelin' You, Pt. 2 (feat. N.O.R.E.)",
   "artist": "Solange",
   "videoId": "q-99tCsJ-nc",
   "duration": "4:07"
  },
  {
   "title": "Ain't No Way",
   "artist": "Solange",
   "videoId": "Gy3H6SqLENU",
   "duration": "3:45"
  },
  {
   "title": "Dance With You (feat. B2K)",
   "artist": "Solange",
   "videoId": "EobaEuJQMoc",
   "duration": "3:04"
  },
  {
   "title": "Get Together",
   "artist": "Solange",
   "videoId": "db-TTdJfjq0",
   "duration": "4:16"
  },
  {
   "title": "Crush",
   "artist": "Solange",
   "videoId": "dZPggu3thfg",
   "duration": "4:34"
  },
  {
   "title": "So Be It",
   "artist": "Solange",
   "videoId": "h41kkzEM4yE",
   "duration": "4:09"
  },
  {
   "title": "True Love (feat. Lil' Romeo)",
   "artist": "Solange",
   "videoId": "7TtMgTH-r1w",
   "duration": "3:50"
  },
  {
   "title": "Feel Good Song",
   "artist": "Solange",
   "videoId": "u_fvDuSi-aE",
   "duration": "3:29"
  },
  {
   "title": "Wonderland",
   "artist": "Solange",
   "videoId": "vaFMfbIHPoY",
   "duration": "4:04"
  },
  {
   "title": "This Could Be Love",
   "artist": "Solange",
   "videoId": "Gq5xCFybsWs",
   "duration": "4:05"
  },
  {
   "title": "Feelin' You, Pt. 1",
   "artist": "Solange",
   "videoId": "7Ce6_miJlkU",
   "duration": "3:23"
  },
  {
   "title": "Just Like You",
   "artist": "Solange",
   "videoId": "58m39JJ-pzg",
   "duration": "3:37"
  },
  {
   "title": "Thinkin' About You (feat. Murphy Lee)",
   "artist": "Solange",
   "videoId": "aVDnqEjHHQY",
   "duration": "4:05"
  },
  {
   "title": "Solo Star",
   "artist": "Solange",
   "videoId": "en8i-YPEe8M",
   "duration": "3:15"
  },
  {
   "title": "I Used To",
   "artist": "Solange",
   "videoId": "T6DVXxCKhK0",
   "duration": "3:28"
  },
  {
   "title": "Sky Away",
   "artist": "Solange",
   "videoId": "bCe0z_SXQyQ",
   "duration": "3:56"
  },
  {
   "title": "This Song's For You",
   "artist": "Solange",
   "videoId": "85ic-eGzgXM",
   "duration": "3:22"
  },
  {
   "title": "Naive (feat. Beyoncé)",
   "artist": "Solange",
   "videoId": "KxmxkheqP2A",
   "duration": "3:47"
  },
  {
   "title": "Feelin' You, Pt. 2 (Chopped & Screwed)",
   "artist": "Solange",
   "videoId": "KoTfm8E4_C0",
   "duration": "5:09"
  },
  {
   "title": "Feelin' You, Pt. 2 (Instrumental)",
   "artist": "Solange",
   "videoId": "SbxBGVdh5qE",
   "duration": "4:09"
  },
  {
   "title": "Ain't No Way (Instrumental)",
   "artist": "Solange",
   "videoId": "QyZtwc421zE",
   "duration": "3:46"
  },
  {
   "title": "Dance With You (Instrumental)",
   "artist": "Solange",
   "videoId": "tp_TDBebqfY",
   "duration": "3:20"
  },
  {
   "title": "Get Together (Instrumental)",
   "artist": "Solange",
   "videoId": "2U00iqtZmEU",
   "duration": "4:18"
  },
  {
   "title": "Crush (Instrumental)",
   "artist": "Solange",
   "videoId": "SY-zJ1BWUDk",
   "duration": "4:35"
  },
  {
   "title": "So Be It (Instrumental)",
   "artist": "Solange",
   "videoId": "YCOEI2sDMdA",
   "duration": "4:09"
  },
  {
   "title": "True Love (Instrumental)",
   "artist": "Solange",
   "videoId": "j59KKYXGiGo",
   "duration": "3:49"
  },
  {
   "title": "Feel Good Song (Instrumental)",
   "artist": "Solange",
   "videoId": "rs_OPTSm9MY",
   "duration": "3:30"
  },
  {
   "title": "Wonderland (Instrumental)",
   "artist": "Solange",
   "videoId": "eBbFtOlkcus",
   "duration": "4:04"
  },
  {
   "title": "This Could Be Love (Instrumental)",
   "artist": "Solange",
   "videoId": "o3IopowEjPw",
   "duration": "4:04"
  },
  {
   "title": "Feelin' You, Pt. 1 (Instrumental)",
   "artist": "Solange",
   "videoId": "h6643s_0G7g",
   "duration": "3:24"
  },
  {
   "title": "Just Like You (Instrumental)",
   "artist": "Solange",
   "videoId": "cejw3UARRtE",
   "duration": "3:27"
  },
  {
   "title": "Thinkin' About You (Instrumental)",
   "artist": "Solange",
   "videoId": "1_afJV9YuBQ",
   "duration": "4:05"
  },
  {
   "title": "Solo Star (Instrumental)",
   "artist": "Solange",
   "videoId": "BqIc7YVzr9o",
   "duration": "3:14"
  },
  {
   "title": "I Used To (Instrumental)",
   "artist": "Solange",
   "videoId": "zSVg859t7JQ",
   "duration": "3:27"
  },
  {
   "title": "Sky Away (Instrumental)",
   "artist": "Solange",
   "videoId": "vmY1BCJdV-4",
   "duration": "3:56"
  },
  {
   "title": "This Song's For You (Instrumental)",
   "artist": "Solange",
   "videoId": "PqWVJ4Vk3B8",
   "duration": "3:22"
  },
  {
   "title": "Naive (Instrumental)",
   "artist": "Solange",
   "videoId": "4fCKNbHzW0w",
   "duration": "3:47"
  }
 ],
 "browseId": "MPREb_qFMO1cILZIh",
 "syncedAt": "2026-03-16T08:58:39.946846Z"
}