{
 "title": "Sounds of My World",
 "artist": "Juls",
 "year": "2021",
 "trackCount": 15,
 "tracks": [
  {
   "title": "Close To Me (feat. WizKid & Jael)",
   "artist": "Juls;Agent Sasco (Assassin)",
   "videoId": "ewpjxs-Itss",
   "duration": "3:01"
  },
  {
   "title": "Summer In The Ends",
   "artist": "Juls, Jaz Karis, & George the Poet",
   "videoId": "VVShNlSurDE",
   "duration": "4:48"
  },
  {
   "title": "Makossa Riddim",
   "artist": "Juls;Haile",
   "videoId": "T-jSme2PKGc",
   "duration": "3:03"
  },
  {
   "title": "Love Me",
   "artist": "Juls;Niniola",
   "videoId": "UgXQWbMTHVg",
   "duration": "2:55"
  },
  {
   "title": "My Size (feat. DarkoVibes & Joey B)",
   "artist": "Juls;King Promise",
   "videoId": "Angvt3NXU6I",
   "duration": "3:46"
  },
  {
   "title": "Intentionally",
   "artist": "Juls & Fireboy DML",
   "videoId": "7rgM7HklOPU",
   "duration": "2:42"
  },
  {
   "title": "Wish You",
   "artist": "Juls;Bas;Mannywellz",
   "videoId": "ehR8ElqiESE",
   "duration": "2:55"
  },
  {
   "title": "Wicked (feat. kadiata & Sam Wise)",
   "artist": "Juls;Knucks",
   "videoId": "pATAtfKYcpM",
   "duration": "3:10"
  },
  {
   "title": "Alarm",
   "artist": "Juls;prettyboydo;Suspect OTB",
   "videoId": "WYqYN8EDFIQ",
   "duration": "2:31"
  },
  {
   "title": "Mare",
   "artist": "Juls & Sauti Sol",
   "videoId": "pmbGhr9qg0g",
   "duration": "3:30"
  },
  {
   "title": "Love Language",
   "artist": "Juls;Mayra Andrade",
   "videoId": "J3u3MAXnAmo",
   "duration": "3:25"
  },
  {
   "title": "Say You Love Me (feat. Karun & Xenia Manasseh)",
   "artist": "Juls;A2",
   "videoId": "RHgkfmxIcas",
   "duration": "4:05"
  },
  {
   "title": "Melly",
   "artist": "Juls & Oxlade",
   "videoId": "e4u3h9stUWM",
   "duration": "2:29"
  },
  {
   "title": "M.O.O.D",
   "artist": "Juls;Kojo Funds",
   "videoId": "noYcmPfJrho",
   "duration": "3:02"
  },
  {
   "title": "Chance",
   "artist": "Juls;Projexx;Tay Iwar",
   "videoId": "_s1WO1FikOg",
   "duration": "3:46"
  }
 ],
 "browseId": "MPREb_d7FKX8rZP6J",
 "syncedAt": "2026-05-31T01:47:58.212420Z"
}