{
 "title": "Freedom's Goblin",
 "artist": "Ty Segall",
 "year": "2018",
 "trackCount": 19,
 "tracks": [
  {
   "title": "Fanny Dog",
   "artist": "Ty Segall",
   "videoId": "Bq4xsMM0QiE",
   "duration": "3:40"
  },
  {
   "title": "Rain",
   "artist": "Ty Segall",
   "videoId": "t_2QA7dhvEE",
   "duration": "4:06"
  },
  {
   "title": "Every 1's a Winner",
   "artist": "Ty Segall",
   "videoId": "4o3vqnKZCCs",
   "duration": "4:19"
  },
  {
   "title": "Despoiler of Cadaver",
   "artist": "Ty Segall",
   "videoId": "oWDKts8eESY",
   "duration": "3:53"
  },
  {
   "title": "When Mommy Kills You",
   "artist": "Ty Segall",
   "videoId": "k8tYytGfQ4M",
   "duration": "2:48"
  },
  {
   "title": "My Lady's On Fire",
   "artist": "Ty Segall",
   "videoId": "zP39XzLrWew",
   "duration": "3:53"
  },
  {
   "title": "Alta",
   "artist": "Ty Segall",
   "videoId": "nYz6_KopGDw",
   "duration": "4:08"
  },
  {
   "title": "Meaning",
   "artist": "Ty Segall",
   "videoId": "Kepya_C1ruc",
   "duration": "3:07"
  },
  {
   "title": "Cry Cry Cry",
   "artist": "Ty Segall",
   "videoId": "-yqMlug5Rhk",
   "duration": "3:13"
  },
  {
   "title": "Shoot You Up",
   "artist": "Ty Segall",
   "videoId": "Qjz5EtKCIXI",
   "duration": "3:21"
  },
  {
   "title": "You Say All The Nice Things",
   "artist": "Ty Segall",
   "videoId": "Td_Ubmx9jEI",
   "duration": "4:23"
  },
  {
   "title": "The Last Waltz",
   "artist": "Ty Segall",
   "videoId": "uiMpy-vPSLU",
   "duration": "2:25"
  },
  {
   "title": "She",
   "artist": "Ty Segall",
   "videoId": "bxSxd3eqTgA",
   "duration": "6:23"
  },
  {
   "title": "Prison",
   "artist": "Ty Segall",
   "videoId": "AlFqsYqAsIM",
   "duration": "1:07"
  },
  {
   "title": "Talkin 3",
   "artist": "Ty Segall",
   "videoId": "FbkvIuRe3Bk",
   "duration": "2:03"
  },
  {
   "title": "The Main Pretender",
   "artist": "Ty Segall",
   "videoId": "6pDw3yV8Ipo",
   "duration": "3:00"
  },
  {
   "title": "I'm Free",
   "artist": "Ty Segall",
   "videoId": "k7X7fXe_kfM",
   "duration": "2:43"
  },
  {
   "title": "5 Ft. Tall (feat. Tall)",
   "artist": "Ty Segall",
   "videoId": "6dnlVvDkKE4",
   "duration": "4:34"
  },
  {
   "title": "And, Goodnight",
   "artist": "Ty Segall",
   "videoId": "xge58nkSoVE",
   "duration": "12:03"
  }
 ],
 "browseId": "MPREb_P2xaYRIsjyD",
 "syncedAt": "2026-03-08T08:53:48.318363Z"
}