{
 "title": "OUTSPOKEN",
 "artist": "SBTRKT",
 "year": "2024",
 "trackCount": 5,
 "tracks": [
  {
   "title": "OUTSPOKEN",
   "artist": "SBTRKT",
   "videoId": "khWcZqBRszQ",
   "duration": "3:08"
  },
  {
   "title": "CLASSIC THEME",
   "artist": "SBTRKT",
   "videoId": "3pVuuOVaIsw",
   "duration": "6:05"
  },
  {
   "title": "BACK ON",
   "artist": "SBTRKT",
   "videoId": "xuWS5t6Av8s",
   "duration": "3:22"
  },
  {
   "title": "VOLCA",
   "artist": "SBTRKT",
   "videoId": "Fv-KTRArDqQ",
   "duration": "3:07"
  },
  {
   "title": "BET YOU NEVER",
   "artist": "SBTRKT",
   "videoId": "jFXHhUsOTaY",
   "duration": "3:52"
  }
 ],
 "browseId": "MPREb_xJDglyRdrS9",
 "syncedAt": "2026-05-31T06:21:49.706541Z"
}