{
 "title": "Ofertório (Ao Vivo) (feat. Tom Veloso)",
 "artist": "Caetano Veloso",
 "year": "2018",
 "trackCount": 28,
 "tracks": [
  {
   "title": "Alegria, Alegria (Ao Vivo) (feat. Tom Veloso)",
   "artist": "Caetano Veloso;Moreno Veloso;Zeca Veloso",
   "videoId": "X06LX7JOAH4",
   "duration": "2:40"
  },
  {
   "title": "O Seu Amor (Ao Vivo) (feat. Moreno Veloso)",
   "artist": "Caetano Veloso;Zeca Veloso;Tom Veloso",
   "videoId": "x-yOqcqOshQ",
   "duration": "4:10"
  },
  {
   "title": "Boas Vindas (Ao Vivo)",
   "artist": "Caetano Veloso;Moreno Veloso;Tom Veloso",
   "videoId": "-jojWracvKI",
   "duration": "3:00"
  },
  {
   "title": "Todo Homem (Ao Vivo) (feat. Tom Veloso)",
   "artist": "Zeca Veloso;Caetano Veloso;Moreno Veloso",
   "videoId": "yRqyteAxft8",
   "duration": "3:42"
  },
  {
   "title": "Genipapo Absoluto (Ao Vivo) (feat. Tom Veloso)",
   "artist": "Caetano Veloso;Moreno Veloso;Zeca Veloso",
   "videoId": "PG6UNGoK3Dc",
   "duration": "2:16"
  },
  {
   "title": "Um Passo À Frente (Ao Vivo)",
   "artist": "Caetano Veloso;Moreno Veloso",
   "videoId": "JUgwWlggl1c",
   "duration": "4:32"
  },
  {
   "title": "Clarão (Ao Vivo)",
   "artist": "Caetano Veloso;Tom Veloso",
   "videoId": "D8rXmSd9_rw",
   "duration": "3:10"
  },
  {
   "title": "De Tentar Voltar (Ao Vivo)",
   "artist": "Moreno Veloso;Tom Veloso",
   "videoId": "51BPbkCyFko",
   "duration": "3:28"
  },
  {
   "title": "A Tua Presença Morena (Ao Vivo)",
   "artist": "Caetano Veloso;Moreno Veloso",
   "videoId": "h95GenPrdsI",
   "duration": "2:07"
  },
  {
   "title": "Trem Das Cores (Ao Vivo)",
   "artist": "Caetano Veloso;Moreno Veloso",
   "videoId": "dm23G53xFjY",
   "duration": "2:59"
  },
  {
   "title": "Um Só Lugar (Ao Vivo)",
   "artist": "Moreno Veloso;Tom Veloso",
   "videoId": "ZfZHaQNQbKg",
   "duration": "2:58"
  },
  {
   "title": "Alexandrino (Ao Vivo)",
   "artist": "Caetano Veloso;Moreno Veloso",
   "videoId": "IkzA2XaJWZA",
   "duration": "2:36"
  },
  {
   "title": "Oração Ao Tempo (Ao Vivo)",
   "artist": "Caetano Veloso",
   "videoId": "YBg9bDzEEPc",
   "duration": "3:46"
  },
  {
   "title": "Alguém Cantando (Ao Vivo) (feat. Tom Veloso)",
   "artist": "Caetano Veloso;Moreno Veloso;Zeca Veloso",
   "videoId": "dGpFXhpKnZU",
   "duration": "1:45"
  },
  {
   "title": "Ofertório (Ao Vivo)",
   "artist": "Caetano Veloso",
   "videoId": "s4raTb3VfJ0",
   "duration": "1:56"
  },
  {
   "title": "Reconvexo (Ao Vivo)",
   "artist": "Caetano Veloso",
   "videoId": "OF23KiJAMTg",
   "duration": "3:21"
  },
  {
   "title": "Você Me Deu (Ao Vivo)",
   "artist": "Caetano Veloso;Zeca Veloso;Tom Veloso",
   "videoId": "qGyOkQzZGSU",
   "duration": "3:23"
  },
  {
   "title": "O Leãozinho (Ao Vivo Em São Paulo / 2017)",
   "artist": "Caetano Veloso;Moreno Veloso",
   "videoId": "3d7xVTSqvmA",
   "duration": "2:57"
  },
  {
   "title": "Gente (Ao Vivo)",
   "artist": "Caetano Veloso",
   "videoId": "pq7BsJkXCsA",
   "duration": "3:32"
  },
  {
   "title": "Ninguém Viu (Ao Vivo)",
   "artist": "Caetano Veloso;Moreno Veloso",
   "videoId": "EFL7BShBwdA",
   "duration": "2:28"
  },
  {
   "title": "Ela E Eu (Ao Vivo)",
   "artist": "Caetano Veloso;Tom Veloso",
   "videoId": "T8iKnpM62eY",
   "duration": "2:59"
  },
  {
   "title": "Não Me Arrependo (Ao Vivo)",
   "artist": "Caetano Veloso;Zeca Veloso;Tom Veloso",
   "videoId": "pkdPxLQFcSU",
   "duration": "3:52"
  },
  {
   "title": "Um Canto De Afoxé Para O Bloco Do Ilê (Ao Vivo) (feat. Zeca Veloso)",
   "artist": "Caetano Veloso;Moreno Veloso;Tom Veloso",
   "videoId": "xo1anVBnf0I",
   "duration": "2:32"
  },
  {
   "title": "Força Estranha (Ao Vivo) (feat. Tom Veloso)",
   "artist": "Caetano Veloso;Moreno Veloso;Zeca Veloso",
   "videoId": "u69R9Bris-I",
   "duration": "3:25"
  },
  {
   "title": "How Beautiful Could A Being Be (Ao Vivo)",
   "artist": "Caetano Veloso",
   "videoId": "yOP9KoN_jIQ",
   "duration": "3:42"
  },
  {
   "title": "Canto Do Povo De Um Lugar / Um Tom (Ao Vivo)",
   "artist": "Caetano Veloso;Moreno Veloso;Zeca Veloso;Tom Veloso",
   "videoId": "I8PpDwz579Q",
   "duration": "3:48"
  },
  {
   "title": "Deusa Do Amor (Ao Vivo)",
   "artist": "Caetano Veloso;Moreno Veloso",
   "videoId": "6UE3U9IOTgk",
   "duration": "4:55"
  },
  {
   "title": "Tá Escrito (Ao Vivo)",
   "artist": "Caetano Veloso;Moreno Veloso;Zeca Veloso;Tom Veloso",
   "videoId": "_rqqNTCsJhM",
   "duration": "2:34"
  }
 ],
 "browseId": "MPREb_sReSW6J9DaE",
 "syncedAt": "2026-03-08T08:53:48.318363Z"
}