{
 "title": "Kwaidan (2023 Remaster)",
 "artist": "Meitei",
 "year": "2023",
 "trackCount": 12,
 "tracks": [
  {
   "title": "Sazanami (2023 Remaster)",
   "artist": "Meitei",
   "videoId": "ce3Vqje3gws",
   "duration": "1:02"
  },
  {
   "title": "Curio (2023 Remaster)",
   "artist": "Meitei",
   "videoId": "ae4aDFdiLGo",
   "duration": "4:23"
  },
  {
   "title": "Touba (2023 Remaster)",
   "artist": "Meitei",
   "videoId": "YHFzJYnwCuE",
   "duration": "4:49"
  },
  {
   "title": "Jizo (2023 Remaster)",
   "artist": "Meitei",
   "videoId": "GDd8wxOD-9U",
   "duration": "4:45"
  },
  {
   "title": "Aoyagi (2023 Remaster)",
   "artist": "Meitei",
   "videoId": "TMOuaJvYRqY",
   "duration": "2:40"
  },
  {
   "title": "Mōryō (2023 Remaster)",
   "artist": "Meitei",
   "videoId": "QEVcScYBBq8",
   "duration": "4:11"
  },
  {
   "title": "Sankai (2023 Remaster)",
   "artist": "Meitei",
   "videoId": "uGbTBZCwdL8",
   "duration": "4:19"
  },
  {
   "title": "Shoji (2023 Remaster)",
   "artist": "Meitei",
   "videoId": "ooVtAmQkUUI",
   "duration": "3:13"
  },
  {
   "title": "Mushiro (2023 Remaster)",
   "artist": "Meitei",
   "videoId": "Sg6SLCs7yQQ",
   "duration": "5:40"
  },
  {
   "title": "Tsukumo",
   "artist": "Meitei",
   "videoId": "U9w2dDyjj9Y",
   "duration": "2:52"
  },
  {
   "title": "Namida",
   "artist": "Meitei",
   "videoId": "IVnCDpx_VpM",
   "duration": "3:14"
  },
  {
   "title": "Kaikyō",
   "artist": "Meitei",
   "videoId": "KM49Jq8PKTk",
   "duration": "1:33"
  }
 ],
 "browseId": "MPREb_74SazHB6EIr",
 "syncedAt": "2026-03-08T08:53:48.318363Z"
}