{
 "title": "Yeezus",
 "artist": "Kanye West",
 "year": "2013",
 "trackCount": 10,
 "tracks": [
  {
   "title": "On Sight",
   "artist": "Kanye West",
   "videoId": "uU9Fe-WXew4",
   "duration": "2:37"
  },
  {
   "title": "Black Skinhead",
   "artist": "Kanye West",
   "videoId": "LXeQ6bmV7oU",
   "duration": "3:09"
  },
  {
   "title": "I Am A God",
   "artist": "Kanye West",
   "videoId": "KuQoQgL63Xo",
   "duration": "3:52"
  },
  {
   "title": "New Slaves",
   "artist": "Kanye West",
   "videoId": "vQ0u09mFodw",
   "duration": "4:17"
  },
  {
   "title": "Hold My Liquor",
   "artist": "Kanye West",
   "videoId": "bvBfiRWLj_0",
   "duration": "5:27"
  },
  {
   "title": "I'm In It",
   "artist": "Kanye West",
   "videoId": "_jZuz3NEr18",
   "duration": "3:55"
  },
  {
   "title": "Blood On The Leaves",
   "artist": "Kanye West",
   "videoId": "KEA0btSNkpw",
   "duration": "6:00"
  },
  {
   "title": "Guilt Trip",
   "artist": "Kanye West",
   "videoId": "5hthMeEqf40",
   "duration": "4:04"
  },
  {
   "title": "Send It Up",
   "artist": "Kanye West",
   "videoId": "vUFiVwa6U_c",
   "duration": "2:59"
  },
  {
   "title": "Bound 2",
   "artist": "Kanye West",
   "videoId": "5gjKuISTMRE",
   "duration": "3:50"
  }
 ],
 "browseId": "MPREb_uR76QxVTBOB",
 "syncedAt": "2026-03-08T08:53:48.318363Z"
}