{
 "title": "The Touch of Your Lips (feat. Doug Raney & Niels-Henning Ørsted Pedersen)",
 "artist": "Chet Baker",
 "year": "1979",
 "trackCount": 7,
 "tracks": [
  {
   "title": "I Waited for You (feat. Doug Raney & Niels-Henning Ørsted Pedersen)",
   "artist": "Chet Baker",
   "videoId": "KAC5rqhqSz0",
   "duration": "8:09"
  },
  {
   "title": "But Not for Me (feat. Doug Raney & Niels-Henning Ørsted Pedersen)",
   "artist": "Chet Baker",
   "videoId": "d2Tu1gAbJ2E",
   "duration": "6:05"
  },
  {
   "title": "Autumn in New York (Take 1) (feat. Doug Raney & Niels-Henning Ørsted Pedersen)",
   "artist": "Chet Baker",
   "videoId": "MC1nG_2bSuc",
   "duration": "5:58"
  },
  {
   "title": "Blue Room (feat. Doug Raney & Niels-Henning Ørsted Pedersen)",
   "artist": "Chet Baker",
   "videoId": "HngI5Gx7HEo",
   "duration": "8:41"
  },
  {
   "title": "The Touch of Your Lips (feat. Doug Raney & Niels-Henning Ørsted Pedersen)",
   "artist": "Chet Baker",
   "videoId": "P2ND9O6tjyE",
   "duration": "8:20"
  },
  {
   "title": "Star Eyes (feat. Doug Raney & Niels-Henning Ørsted Pedersen)",
   "artist": "Chet Baker",
   "videoId": "0LVa7larMUE",
   "duration": "5:46"
  },
  {
   "title": "Autumn in New York (Take 2) (feat. Doug Raney & Niels-Henning Ørsted Pedersen)",
   "artist": "Chet Baker",
   "videoId": "QbbQlkeT2ng",
   "duration": "4:48"
  }
 ],
 "browseId": "MPREb_qIgUohCPiSd",
 "syncedAt": "2026-03-08T08:53:48.318363Z"
}