{
 "title": "With No Due Respect",
 "artist": "Foggieraw",
 "year": "2026",
 "trackCount": 17,
 "tracks": [
  {
   "title": "Unisex",
   "artist": "Foggieraw",
   "videoId": "rDdWjH7QRaM",
   "duration": "1:49"
  },
  {
   "title": "Faith Lies",
   "artist": "Foggieraw",
   "videoId": "55bs0r0q4mw",
   "duration": "3:45"
  },
  {
   "title": "Rookie of the Year",
   "artist": "Foggieraw",
   "videoId": "Ufnr-AbYvzg",
   "duration": "2:30"
  },
  {
   "title": "Mo Money Than Ur Dad",
   "artist": "Foggieraw;KARRAHBOOO",
   "videoId": "oYRgj646CFA",
   "duration": "2:25"
  },
  {
   "title": "Cadillac",
   "artist": "Foggieraw & Harry Fraud",
   "videoId": "kkpaR2CisIs",
   "duration": "2:34"
  },
  {
   "title": "Disrespectfully Decline",
   "artist": "Foggieraw & Larry June",
   "videoId": "C8Mp-RJHbbA",
   "duration": "3:14"
  },
  {
   "title": "Love Don’t Cost A Thing",
   "artist": "Foggieraw",
   "videoId": "CrfTxvOfHwg",
   "duration": "3:27"
  },
  {
   "title": "Stay Awhile (feat. Ari Lennox)",
   "artist": "Foggieraw",
   "videoId": "thcUDgXxtV8",
   "duration": "4:01"
  },
  {
   "title": "Water2wine.mp3",
   "artist": "Foggieraw",
   "videoId": "fcUHI7A75sQ",
   "duration": "3:50"
  },
  {
   "title": "Huey and Riley",
   "artist": "Foggieraw",
   "videoId": "m68FoaGTo4E",
   "duration": "1:55"
  },
  {
   "title": "Grow Up",
   "artist": "Foggieraw & John Legend",
   "videoId": "VAyu7J6mhfI",
   "duration": "3:19"
  },
  {
   "title": "Boyfriend In Yo Brain (Notice Me)",
   "artist": "Foggieraw",
   "videoId": "qHJnIul5aOk",
   "duration": "2:48"
  },
  {
   "title": "Thinking With My Heart",
   "artist": "Foggieraw",
   "videoId": "AiRyTs-Q_jM",
   "duration": "2:44"
  },
  {
   "title": "Psalm and Islam",
   "artist": "Foggieraw, Dave James, & Gwen Bunn",
   "videoId": "h12gGP7uLkY",
   "duration": "3:49"
  },
  {
   "title": "Psalm 62",
   "artist": "Foggieraw",
   "videoId": "kEwia3LGi88",
   "duration": "2:52"
  },
  {
   "title": "Grandmas & Grandpas",
   "artist": "Foggieraw",
   "videoId": "SVxLU0kttsk",
   "duration": "3:05"
  },
  {
   "title": "Bitchertation",
   "artist": "Foggieraw",
   "videoId": "im7lr56WakI",
   "duration": "3:44"
  }
 ],
 "browseId": "MPREb_f0vSveqKvO2",
 "syncedAt": "2026-03-08T08:53:48.318363Z"
}