{
 "title": "Hitler Wears Hermes 8: Side B",
 "artist": "Westside Gunn",
 "year": "2021",
 "trackCount": 20,
 "tracks": [
  {
   "title": "Brodie Lee",
   "artist": "Westside Gunn",
   "videoId": "dlLlnqxoJqU",
   "duration": "0:32"
  },
  {
   "title": "End how You start intro",
   "artist": "Westside Gunn",
   "videoId": "o2OERUUmkpo",
   "duration": "3:48"
  },
  {
   "title": "Hell on Earth, Pt. 2 (feat. Benny The Butcher & Conway The Machine)",
   "artist": "Westside Gunn",
   "videoId": "jhj1XdYkC3A",
   "duration": "3:56"
  },
  {
   "title": "Free Kutter (feat. Jay Electronica)",
   "artist": "Westside Gunn",
   "videoId": "txBHI5362l8",
   "duration": "2:50"
  },
  {
   "title": "Richies",
   "artist": "Westside Gunn",
   "videoId": "xcRPX0VADRs",
   "duration": "3:37"
  },
  {
   "title": "Julia Lang (feat. Trap-A-Holics)",
   "artist": "Westside Gunn",
   "videoId": "x4rSiPFBPoU",
   "duration": "2:07"
  },
  {
   "title": "Celine Pour Homme (feat. Heem, Chase Fetti & Flee Lord)",
   "artist": "Westside Gunn",
   "videoId": "bfhbOZJoooc",
   "duration": "5:52"
  },
  {
   "title": "Best Dressed Demons (feat. Mach-Hommy)",
   "artist": "Westside Gunn",
   "videoId": "_8X5LmUkmdU",
   "duration": "2:40"
  },
  {
   "title": "Forest Lawn (feat. 2 Chainz & Armani Caesar)",
   "artist": "Westside Gunn",
   "videoId": "jqyl4Y78yXs",
   "duration": "5:02"
  },
  {
   "title": "Why I do em Like that (feat. Billie Essco)",
   "artist": "Westside Gunn",
   "videoId": "SPHiol5-upY",
   "duration": "4:01"
  },
  {
   "title": "RIP Bergdorf (feat. Mach-Hommy)",
   "artist": "Westside Gunn",
   "videoId": "J29UW6SdJ80",
   "duration": "2:08"
  },
  {
   "title": "TV BOY",
   "artist": "Westside Gunn",
   "videoId": "02-w9Y1AQkw",
   "duration": "2:27"
  },
  {
   "title": "Survivor Series 95 (feat. Jay Worthy & Larry June)",
   "artist": "Westside Gunn",
   "videoId": "_i_Pl55u-TM",
   "duration": "7:08"
  },
  {
   "title": "Eddie Kingston (feat. Rome Streetz)",
   "artist": "Westside Gunn",
   "videoId": "K8d0lB_yUSE",
   "duration": "3:08"
  },
  {
   "title": "Ostertag (feat. Stove God Cooks)",
   "artist": "Westside Gunn",
   "videoId": "VgrO0ZLgTV4",
   "duration": "2:13"
  },
  {
   "title": "Munch (feat. Tiona Deniece)",
   "artist": "Westside Gunn",
   "videoId": "rCsWSoVzuZY",
   "duration": "2:32"
  },
  {
   "title": "99 Avirex (feat. Stove God Cooks & AZ)",
   "artist": "Westside Gunn",
   "videoId": "U8zOnkQrsWs",
   "duration": "4:27"
  },
  {
   "title": "The Fly who couldn't Fly straight (feat. Tyler, The Creator, Tyler & The Creator)",
   "artist": "Westside Gunn",
   "videoId": "fw1U17XRa50",
   "duration": "1:46"
  },
  {
   "title": "Big AL (feat. Rome Streetz)",
   "artist": "Westside Gunn",
   "videoId": "62u6HLmwqQg",
   "duration": "2:36"
  },
  {
   "title": "BYE BYE (feat. Keisha Plum)",
   "artist": "Westside Gunn",
   "videoId": "xbFwkLHETXQ",
   "duration": "1:07"
  }
 ],
 "browseId": "MPREb_n875tkBIIxM",
 "syncedAt": "2026-03-08T08:53:48.318363Z"
}