{
 "title": "Dawn",
 "artist": "Emma Donovan",
 "year": "2014",
 "trackCount": 9,
 "tracks": [
  {
   "title": "Black Woman",
   "artist": "Emma Donovan;The PutBacks",
   "videoId": "DoXcJSygBVk",
   "duration": "5:10"
  },
  {
   "title": "My Goodness",
   "artist": "Emma Donovan;The PutBacks",
   "videoId": "A5bN0hB6db8",
   "duration": "3:57"
  },
  {
   "title": "Dawn",
   "artist": "Emma Donovan;The PutBacks",
   "videoId": "afKrbtY71LI",
   "duration": "3:53"
  },
  {
   "title": "Mother",
   "artist": "Emma Donovan;The PutBacks",
   "videoId": "LS9aIMCSj1s",
   "duration": "5:39"
  },
  {
   "title": "Daddy",
   "artist": "Emma Donovan;The PutBacks",
   "videoId": "wLDofxZpQcE",
   "duration": "3:50"
  },
  {
   "title": "Keep Me in Your Reach",
   "artist": "Emma Donovan;The PutBacks",
   "videoId": "UyDnloW5FbY",
   "duration": "4:21"
  },
  {
   "title": "Come Back to Me",
   "artist": "Emma Donovan;The PutBacks",
   "videoId": "clocpqAuX6o",
   "duration": "5:20"
  },
  {
   "title": "Voodoo",
   "artist": "Emma Donovan;The PutBacks",
   "videoId": "9USbozWcAqA",
   "duration": "3:44"
  },
  {
   "title": "Over Under Away",
   "artist": "Emma Donovan;The PutBacks",
   "videoId": "i2B1uJKoJtE",
   "duration": "4:59"
  }
 ],
 "browseId": "MPREb_YUi9r1DEqg2",
 "syncedAt": "2026-03-08T08:53:48.318363Z"
}