{
 "title": "Ghosts EP",
 "artist": "V.I.V.E.K",
 "year": "2024",
 "trackCount": 4,
 "tracks": [
  {
   "title": "Ghosts",
   "artist": "V.I.V.E.K",
   "videoId": "_jaBXI8-NDY",
   "duration": "4:14"
  },
  {
   "title": "Back Then",
   "artist": "V.I.V.E.K",
   "videoId": "8Gtq27zFjIg",
   "duration": "4:11"
  },
  {
   "title": "TEK1",
   "artist": "V.I.V.E.K",
   "videoId": "3jLaYSaVk9k",
   "duration": "6:33"
  },
  {
   "title": "Garrison",
   "artist": "V.I.V.E.K",
   "videoId": "qLS8wMq-BYw",
   "duration": "3:43"
  }
 ],
 "browseId": "MPREb_8lVtKnPmjkk",
 "syncedAt": "2026-04-02T08:58:49.973204Z"
}