{
 "title": "Bando Stone and The New World",
 "artist": "Childish Gambino",
 "year": "2024",
 "trackCount": 17,
 "tracks": [
  {
   "title": "H3@RT$ W3RE M3@NT T0 F7¥",
   "artist": "Childish Gambino",
   "videoId": "FoHRhPMrRtA",
   "duration": "3:08"
  },
  {
   "title": "Lithonia",
   "artist": "Childish Gambino",
   "videoId": "_7GVjIF08_c",
   "duration": "2:59"
  },
  {
   "title": "Survive (feat. Chlöe)",
   "artist": "Childish Gambino",
   "videoId": "wI1icV6OTc0",
   "duration": "4:08"
  },
  {
   "title": "Steps Beach",
   "artist": "Childish Gambino",
   "videoId": "SM7ESDpGDNE",
   "duration": "3:49"
  },
  {
   "title": "Talk My Shit (feat. Amaarae & Flo Milli)",
   "artist": "Childish Gambino",
   "videoId": "aN6c7_g3jfY",
   "duration": "3:46"
  },
  {
   "title": "Got To Be",
   "artist": "Childish Gambino",
   "videoId": "0670G-GUIR4",
   "duration": "2:57"
  },
  {
   "title": "Real Love",
   "artist": "Childish Gambino",
   "videoId": "c-NTJ11np2s",
   "duration": "2:18"
  },
  {
   "title": "In The Night (feat. Jorja Smith & Amaarae)",
   "artist": "Childish Gambino",
   "videoId": "IoR8-G6PuiI",
   "duration": "3:50"
  },
  {
   "title": "Yoshinoya",
   "artist": "Childish Gambino",
   "videoId": "RJ2tRAihvXI",
   "duration": "3:23"
  },
  {
   "title": "Can You Feel Me (feat. Legend)",
   "artist": "Childish Gambino",
   "videoId": "fbeEWh3aUkY",
   "duration": "2:59"
  },
  {
   "title": "No Excuses (feat. Ludwig Göransson & Kamasi Washington)",
   "artist": "Childish Gambino",
   "videoId": "Kau1YejhtnU",
   "duration": "7:24"
  },
  {
   "title": "Cruisin' (feat. Yeat)",
   "artist": "Childish Gambino",
   "videoId": "31llKyt6Ls4",
   "duration": "3:59"
  },
  {
   "title": "We Are God",
   "artist": "Childish Gambino",
   "videoId": "kSMUflmrRUE",
   "duration": "4:24"
  },
  {
   "title": "Running Around (feat. Fousheé)",
   "artist": "Childish Gambino",
   "videoId": "wHkux66jzJY",
   "duration": "2:35"
  },
  {
   "title": "Dadvocate",
   "artist": "Childish Gambino",
   "videoId": "265lKeKeuGo",
   "duration": "2:41"
  },
  {
   "title": "Happy Survival",
   "artist": "Childish Gambino & Khruangbin",
   "videoId": "jNAHOjbpa8c",
   "duration": "3:24"
  },
  {
   "title": "A Place Where Love Goes",
   "artist": "Childish Gambino",
   "videoId": "K4412Pxzm20",
   "duration": "2:44"
  }
 ],
 "browseId": "MPREb_UyBn7Wk0a3s",
 "syncedAt": "2026-03-08T08:53:48.318363Z"
}