{
 "title": "In Square Circle",
 "artist": "Stevie Wonder",
 "year": "1985",
 "trackCount": 10,
 "tracks": [
  {
   "title": "Part-Time Lover",
   "artist": "Stevie Wonder",
   "videoId": "MpDM6ygsb20",
   "duration": "4:13"
  },
  {
   "title": "I Love You Too Much",
   "artist": "Stevie Wonder",
   "videoId": "jHmFiK-Zy5I",
   "duration": "5:28"
  },
  {
   "title": "Whereabouts",
   "artist": "Stevie Wonder",
   "videoId": "5xldzgFKVg8",
   "duration": "4:18"
  },
  {
   "title": "Stranger On The Shore Of Love",
   "artist": "Stevie Wonder",
   "videoId": "lWJbAC0okXw",
   "duration": "5:01"
  },
  {
   "title": "Never In Your Sun",
   "artist": "Stevie Wonder",
   "videoId": "My6rvf5sSoY",
   "duration": "4:07"
  },
  {
   "title": "Spiritual Walkers",
   "artist": "Stevie Wonder",
   "videoId": "Bnz3jzJAxkE",
   "duration": "5:14"
  },
  {
   "title": "Land Of La La",
   "artist": "Stevie Wonder",
   "videoId": "4iNHHy3TmLs",
   "duration": "5:13"
  },
  {
   "title": "Go Home",
   "artist": "Stevie Wonder",
   "videoId": "OrmH0jXiAw0",
   "duration": "5:19"
  },
  {
   "title": "Overjoyed",
   "artist": "Stevie Wonder",
   "videoId": "cIhd5Yc5TCY",
   "duration": "3:43"
  },
  {
   "title": "It's Wrong (Apartheid)",
   "artist": "Stevie Wonder",
   "videoId": "wbG3zIs4Q4E",
   "duration": "6:53"
  }
 ],
 "browseId": "MPREb_lQ53woIoqxV",
 "syncedAt": "2026-04-02T08:58:49.973204Z"
}