{
 "title": "Refraction",
 "artist": "MPH",
 "year": "2024",
 "trackCount": 15,
 "tracks": [
  {
   "title": "Pushing (Intro)",
   "artist": "MPH",
   "videoId": "jAFBS6lZbxI",
   "duration": "4:06"
  },
  {
   "title": "Cadence",
   "artist": "MPH",
   "videoId": "7Mk-zgJGs4E",
   "duration": "2:51"
  },
  {
   "title": "Just Like",
   "artist": "MPH",
   "videoId": "S_7qCMrDLKE",
   "duration": "3:26"
  },
  {
   "title": "Brainwashing",
   "artist": "MPH",
   "videoId": "70V6jbV1Pho",
   "duration": "3:24"
  },
  {
   "title": "North LDN",
   "artist": "MPH;Subten",
   "videoId": "Wigk9LdmbcA",
   "duration": "3:15"
  },
  {
   "title": "Intermission",
   "artist": "MPH",
   "videoId": "nfpsIN0O5bc",
   "duration": "1:57"
  },
  {
   "title": "My Mind",
   "artist": "MPH",
   "videoId": "bTxe9TXS_kc",
   "duration": "3:53"
  },
  {
   "title": "Shoot To Kill",
   "artist": "MPH",
   "videoId": "YYK_nRLiutM",
   "duration": "3:48"
  },
  {
   "title": "Lights On",
   "artist": "MPH;AC Slater;Eloise Keeble",
   "videoId": "MomddE5v_jk",
   "duration": "3:14"
  },
  {
   "title": "Records",
   "artist": "MPH",
   "videoId": "XAvkQoo3DJE",
   "duration": "4:30"
  },
  {
   "title": "Over This",
   "artist": "MPH",
   "videoId": "0BJaRgGbcM0",
   "duration": "3:20"
  },
  {
   "title": "Funk Master",
   "artist": "MPH",
   "videoId": "Ek1SnG9W-c4",
   "duration": "3:43"
  },
  {
   "title": "Crowd Rolling",
   "artist": "MPH",
   "videoId": "dKc6MIFRSvY",
   "duration": "4:35"
  },
  {
   "title": "Endorphins",
   "artist": "MPH",
   "videoId": "cc1TLoOfmZo",
   "duration": "3:45"
  },
  {
   "title": "Haunted",
   "artist": "MPH",
   "videoId": "vbCmUnj3nnA",
   "duration": "3:19"
  }
 ],
 "browseId": "MPREb_Z3AUBRnVIL5",
 "syncedAt": "2026-04-02T08:58:49.973204Z"
}