{
 "title": "A LA SALA",
 "artist": "Khruangbin",
 "year": "2024",
 "trackCount": 12,
 "tracks": [
  {
   "title": "Fifteen Fifty-Three",
   "artist": "Khruangbin",
   "videoId": "ZEPUuOGqjwU",
   "duration": "4:08"
  },
  {
   "title": "May Ninth",
   "artist": "Khruangbin",
   "videoId": "upo8_2NdmRI",
   "duration": "3:13"
  },
  {
   "title": "Ada Jean",
   "artist": "Khruangbin",
   "videoId": "3YFhuf0Twpc",
   "duration": "3:20"
  },
  {
   "title": "Farolim de Felgueiras",
   "artist": "Khruangbin",
   "videoId": "NDxQTrhI0Jc",
   "duration": "2:01"
  },
  {
   "title": "Pon Pón",
   "artist": "Khruangbin",
   "videoId": "-e1IZFm_qoc",
   "duration": "2:59"
  },
  {
   "title": "Todavía Viva",
   "artist": "Khruangbin",
   "videoId": "B2m_Jx_rksc",
   "duration": "4:24"
  },
  {
   "title": "Juegos y Nubes",
   "artist": "Khruangbin",
   "videoId": "NOk4qOFpklI",
   "duration": "2:05"
  },
  {
   "title": "Hold Me Up (Thank You)",
   "artist": "Khruangbin",
   "videoId": "EBln5ue2398",
   "duration": "3:50"
  },
  {
   "title": "Caja de la Sala",
   "artist": "Khruangbin",
   "videoId": "k5vAP4OgpNA",
   "duration": "1:50"
  },
  {
   "title": "Three From Two",
   "artist": "Khruangbin",
   "videoId": "LlR0FDLMTD8",
   "duration": "3:35"
  },
  {
   "title": "A Love International",
   "artist": "Khruangbin",
   "videoId": "ZQ9fx_e8Yxg",
   "duration": "4:16"
  },
  {
   "title": "Les Petits Gris",
   "artist": "Khruangbin",
   "videoId": "9AZT5wxMCrE",
   "duration": "4:02"
  }
 ],
 "browseId": "MPREb_M0gnOSIbJ3a",
 "syncedAt": "2026-03-08T08:53:48.318363Z"
}